mkpp/__init__.py
mkpp/__main__.py
mkpp/cli/__init__.py
mkpp/cli/args.py
mkpp/cli/log.py
mkpp-1.0.3.dist-info/entry_points.txt
mkpp-1.0.3.dist-info/WHEEL
mkpp-1.0.3.dist-info/METADATA
mkpp-1.0.3.dist-info/LICENSE
mkpp-1.0.3.dist-info/RECORD
