Metadata-Version: 2.1
Name: mkpp
Version: 1.0.3
Summary: Simple tool for creating Python packages. For lazies.
License: MIT
Keywords: packages
Author-email: jieggii <jieggii.contact@gmail.com>
Requires-Python: >=3.6
Project-URL: Bug tracker, https://github.com/jieggii/mkpp/issues
Project-URL: Homepage, https://github.com/jieggii/mkpp
